comet_postgen/__init__.py
comet_postgen/command.py
comet_postgen/files.py
comet_postgen/gitops.py
comet_postgen/purge.py
comet_postgen/runner.py
comet_postgen/gen_ascii/__init__.py
comet_postgen/gen_ascii/ascii_art.py
comet_postgen/gen_ascii/gen.py
comet_postgen/gen_ascii/frame/__init__.py
comet_postgen/gen_ascii/frame/border.py
comet_postgen/gen_ascii/frame/framer.py
comet_postgen/gen_ascii/frame/width_utils.py
comet_postgen/utils/__init__.py
comet_postgen/utils/common/__init__.py
comet_postgen/utils/common/constants.py
comet_postgen/utils/common/utils.py
comet_postgen/utils/config/__init__.py
comet_postgen/utils/config/config.py
comet_postgen/utils/logging/__init__.py
comet_postgen/utils/logging/log_util.py
comet_postgen-0.2.4.dist-info/METADATA
comet_postgen-0.2.4.dist-info/WHEEL
comet_postgen-0.2.4.dist-info/top_level.txt
comet_postgen-0.2.4.dist-info/RECORD
